signals/__init__.py
signals/global_settings.py
signals/py.typed
signals/dispatch/__init__.py
signals/dispatch/dispatcher.py
signals/test/__init__.py
signals/test/utils.py
signals/utils/__init__.py
signals/utils/inspect.py
signals_py-0.1.0.post1.dist-info/METADATA
signals_py-0.1.0.post1.dist-info/WHEEL
signals_py-0.1.0.post1.dist-info/RECORD
