Metadata-Version: 2.4
Name: signals-py
Version: 0.1.0.post1
Summary: send and receive signals
Project-URL: Homepage, https://github.com/khiyavan/signals-py
Project-URL: Issues, https://github.com/khiyavan/signals-py/issues
Maintainer-email: amirreza <amir.rsf1380@gmail.com>
Classifier: Development Status :: 4 - Beta
Classifier: Intended Audience :: Developers
Classifier: Operating System :: OS Independent
Classifier: Programming Language :: Python
Classifier: Programming Language :: Python :: 3
Classifier: Programming Language :: Python :: 3 :: Only
Classifier: Programming Language :: Python :: 3.12
Classifier: Programming Language :: Python :: 3.13
Classifier: Topic :: Software Development :: Libraries
Classifier: Topic :: Utilities
Classifier: Typing :: Typed
Requires-Python: >=3.12
Requires-Dist: asgiref>=3.8.1
Requires-Dist: lazy-settings>=0.1.1
